okappleapi/__init__.py
okappleapi/apple_api_agent.py
okappleapi/models.py
okappleapi/ok_agent.py
OKAppleAPI-1.5.2.dist-info/METADATA
OKAppleAPI-1.5.2.dist-info/WHEEL
OKAppleAPI-1.5.2.dist-info/top_level.txt
OKAppleAPI-1.5.2.dist-info/RECORD
