Metadata-Version: 2.1
Name: OKAppleAPI
Version: 1.5.2
Summary: OK App Store Connect API
Home-page: https://github.com/shede333/OKAppleAPI
Author: shede333
Author-email: 333wshw@163.com
License: UNKNOWN
Keywords: ios ok apple appstore app store connect api appstoreconnectapi
Platform: UNKNOWN
Classifier: Development Status :: 5 - Production/Stable
Classifier: License :: OSI Approved :: MIT License
Classifier: Operating System :: POSIX
Classifier: Topic :: Software Development :: Libraries :: Python Modules
Classifier: Programming Language :: Python
Classifier: Programming Language :: Python :: 3
Classifier: Programming Language :: Python :: 3.6
Classifier: Programming Language :: Python :: 3.7
Classifier: Programming Language :: Python :: 3.8
Requires-Python: ~=3.7
Requires-Dist: PyJWT~=2.0
Requires-Dist: PyMobileProvision~=1.4
Requires-Dist: requests~=2.20
